failsense/__init__.py
failsense/client.py
failsense/llm.py
failsense-0.1.0.dist-info/licenses/LICENSE
failsense-0.1.0.dist-info/METADATA
failsense-0.1.0.dist-info/WHEEL
failsense-0.1.0.dist-info/top_level.txt
failsense-0.1.0.dist-info/RECORD
